README.md
setup.cfg
setup.py
bin/speakeasy
speakeasy/__init__.py
speakeasy/speakeasy.py
speakeasy/utils.py
speakeasy.egg-info/PKG-INFO
speakeasy.egg-info/SOURCES.txt
speakeasy.egg-info/dependency_links.txt
speakeasy.egg-info/requires.txt
speakeasy.egg-info/top_level.txt
speakeasy/emitter/__init__.py
speakeasy/emitter/simple.py
test/test_speakeasy.py
test/test_speakeasy_legacy.py
test/test_util.py
test/test_zmq_spec.py