Metadata-Version: 1.1
Name: speakeasy
Version: 2.0.0
Summary: Metrics aggregation server
Home-page: https://github.com/etdub/speakeasy
Author: Eric Wong
Author-email: UNKNOWN
License: Apache License 2.0
Platform: UNKNOWN
Classifier: Intended Audience :: Developers
Classifier: Natural Language :: English
Classifier: Programming Language :: Python
Classifier: Programming Language :: Python :: 2.7
Classifier: Programming Language :: Python :: 3
Classifier: Programming Language :: Python :: 3.5
Classifier: Programming Language :: Python :: 3.6
Classifier: Programming Language :: Python :: 3.7
Classifier: License :: OSI Approved :: Apache Software License
